{
  "twitter": {
    "username": "kenroys_lotte",
    "displayName": "Lotteux! le bladeur canc\u00e9reux",
    "twitterId": "3309537761",
    "country": "France",
    "source": "France App Store",
    "profileUrl": "https://x.com/kenroys_lotte"
  },
  "rpb": {
    "userId": "cmk4e0bvn0004rca3zl3ypwl5",
    "secondaryUserId": "onvemTtmLnD5ph1z8Pdkmo8ms32pXQlz",
    "discordTag": "lotteuxsqwa",
    "username": "lotteuxsqwa",
    "displayName": "\ud835\udcc1\ud835\udcab\ud835\udca9 | LOTTEUX!",
    "globalName": "BIG LOTTEUX! (aelita supremacy)",
    "tournamentResults": [
      { "name": "Golden Claw", "score": "0-2", "note": "x2" },
      { "name": "BBT19", "score": "1-2" },
      { "name": "Scarlet Arena", "score": "1-4" }
    ]
  },
  "location": {
    "city": "Lyon",
    "area": "Lyon Est (Bron / Saint-Priest)",
    "postalCodes": ["69500", "69800"],
    "region": "Auvergne-Rh\u00f4ne-Alpes",
    "department": "Rh\u00f4ne (69)",
    "country": "France",
    "coordinates": { "lat": 45.7377, "lon": 4.9184 },
    "source": "confirmed + IP geolocation cross-reference"
  },
  "network": {
    "ip": "5.49.15.7",
    "hostname": "5-49-15-7.hfc.dyn.abo.bbox.fr",
    "subnet": "5.49.14.0/23",
    "isp": "Bouygues Telecom SA",
    "ispType": "Wireline (connexion fixe)",
    "asn": "AS5410",
    "asnName": "BOUYGTEL-ISP",
    "connectionType": "HFC (Hybrid Fiber Coaxial / c\u00e2ble bbox)",
    "ipType": "residential",
    "isDynamic": true,
    "isMobile": false,
    "isProxy": false,
    "isHosting": false,
    "abuse": "abuse@bouyguestelecom.fr",
    "ripeRange": "5.49.0.0 - 5.49.63.255",
    "ripeNetname": "BOUYGTEL-ISP-CABLE",
    "geolocation": {
      "ipinfo": { "city": "Saint-Quentin-en-Yvelines", "region": "\u00cele-de-France", "postal": "78190", "coords": "48.7719, 2.0189" },
      "ipapi_co": { "city": "Saint-Priest", "region": "Auvergne-Rh\u00f4ne-Alpes", "postal": "69800", "coords": "45.6959, 4.9424" },
      "ip_api_com": { "city": "Bron", "region": "Rh\u00f4ne-Alpes", "postal": "69500", "coords": "45.7377, 4.9184" }
    },
    "geoNote": "ipinfo.io impr\u00e9cis (noeud r\u00e9seau Bouygues \u00ceDF). ipapi.co et ip-api.com convergent vers Lyon Est (Bron/Saint-Priest), coh\u00e9rent avec localisation confirm\u00e9e \u00e0 Lyon",
    "traceroute": "Hetzner (serveur) \u2192 Paris \u2192 bbox.fr backbone \u2192 Lyon",
    "hostUp": true,
    "device": "iPhone",
    "os": "iOS 18.6",
    "browser": "Safari 26.0 (Mobile)",
    "userAgent": "Mozilla/5.0 (iPhone; CPU iPhone OS 18_6 like Mac OS X) AppleWebKit/605.1.15 (KHTML, like Gecko) Version/26.0 Mobile/15E148 Safari/604.1",
    "sessions": [
      { "createdAt": "2026-02-05T22:25:52.423Z", "expiresAt": "2026-03-10T00:09:57.592Z" },
      { "createdAt": "2026-02-05T22:25:43.051Z", "expiresAt": "2026-03-07T22:25:43.051Z" },
      { "createdAt": "2026-02-05T22:25:10.447Z", "expiresAt": "2026-03-07T22:25:10.447Z" }
    ]
  },
  "followingStartingWithV": [
    { "username": "Velicto", "name": "\u2764\ufe0fVelicto\ud83e\udd0d", "id": "1730534213437231104", "followers": 1093, "description": "Manga - Jeu-Vid\u00e9o - Kpop - Lecture - Bougie - Foot - Atleti - T1 Overwatch" },
    { "username": "veisatou", "name": "Terra", "id": "1512475250944053257", "followers": 20, "description": "faut que je commence a dessiner pour des gens l\u00e0" },
    { "username": "Villepin", "name": "Dominique de Villepin", "id": "29499020", "followers": 162354, "description": "Ancien Premier ministre de la R\u00e9publique fran\u00e7aise" },
    { "username": "VeaTheMoth", "name": "VeaTheMoth COMISSIONS OPEN!", "id": "1207393119584620545", "followers": 1069, "description": "Artist \ud83c\uddeb\ud83c\uddf7 who loves TMNT/Hazbin hotel/MHA/Pokemon/Genshin" },
    { "username": "vietsupremacy", "name": "\ud835\udc3b\u2606", "id": "1732414777", "followers": 1583, "description": "heart in S\u00e0i G\u00f2n +84 | free palestine" }
  ],
  "tweets": [
    {
      "id": "2021507020340478395",
      "text": "Je pense surtout que \u00e7a n'a rien \u00e0 voir avec le m\u00e9tissage, mais plut\u00f4t les parents hein\ud83e\udd13",
      "createdAt": "2026-02-11T08:50:06Z",
      "replyCount": 0,
      "retweetCount": 1,
      "likeCount": 7,
      "quotedTweet": { "id": "2021328226757312963", "author": "@Jelanidu237" }
    },
    {
      "id": "2021505675160162660",
      "text": "On l'apprend \u00e0 l'\u00e9cole, s'ils savent pas c'est que l'\u00e9cole ne l'a pas fait\ud83e\udd13",
      "createdAt": "2026-02-11T08:44:45Z",
      "replyCount": 1,
      "retweetCount": 0,
      "likeCount": 7,
      "quotedTweet": { "id": "2021484775975026906", "author": "@ImpactMediaFR" }
    },
    {
      "id": "2021298158165176664",
      "text": "Tuer Bad Bunny qui pr\u00f4ne la paix c'est une chose, tuer Kirk le nazi en est une autre\n\nLe pacifisme c'est cool deux minutes, mais un nazi \u00e7a se bute\ud83e\udd13\n\nJe suis compl\u00e8tement ferm\u00e9 \u00e0 l'id\u00e9e de pr\u00f4ner un message de paix \u00e0 des gens qui pensent que ma pr\u00e9sence en soci\u00e9t\u00e9 est une menace",
      "createdAt": "2026-02-10T19:00:09Z",
      "replyCount": 0,
      "retweetCount": 0,
      "likeCount": 1,
      "quotedTweet": { "id": "2021167438172144009", "author": "@FreddyGladieux" }
    },
    {
      "id": "2021239467613306886",
      "text": "RT @Infxmouus: L'entr\u00e9e sur le son est juste l\u00e9gendaire, fallait voir comment j'ai hurl\u00e9",
      "createdAt": "2026-02-10T15:06:56Z",
      "isRetweet": true
    },
    {
      "id": "2021234137672175777",
      "text": "RT @anthonyreungere",
      "createdAt": "2026-02-10T14:45:45Z",
      "isRetweet": true
    },
    {
      "id": "2020844634541523229",
      "text": "RT @X313Army: Il y a 32 ans, la maison de disques des Cranberries a offert \u00e0 Dolores O'Riordan un ch\u00e8que d'un million de dollars...",
      "createdAt": "2026-02-09T12:58:01Z",
      "isRetweet": true
    },
    {
      "id": "2020836420643082343",
      "text": "Golden Claw 0-2 (x2), BBT19 1-2, Scarlet Arena 1-4.\n\nLa f\u00eate est finie. Je vais sucer la meta comme jamais.",
      "createdAt": "2026-02-09T12:25:22Z",
      "replyCount": 3,
      "retweetCount": 0,
      "likeCount": 2,
      "tags": ["beyblade", "tournament"]
    },
    {
      "id": "2020794408317116737",
      "text": "Merci Bad Bunny de repr\u00e9senter les RENOIS de FRANCE t'sais le mec qui veut cr\u00e9er une \u00e9ni\u00e8me fitna",
      "createdAt": "2026-02-09T09:38:26Z",
      "replyCount": 0,
      "retweetCount": 0,
      "likeCount": 1
    },
    {
      "id": "2020790303301517609",
      "text": "Les tiramisu de Masamune (RPB) foudroient les cr\u00eapes d'abdel_bma (LFBX)",
      "createdAt": "2026-02-09T09:22:07Z",
      "replyCount": 2,
      "retweetCount": 0,
      "likeCount": 4,
      "tags": ["beyblade", "rpb"]
    },
    {
      "id": "2020567688284680578",
      "text": "RT @rpb_ey: D\u00e9but du Bey-Tamashii S\u00e9ries 2",
      "createdAt": "2026-02-08T18:37:31Z",
      "isRetweet": true,
      "tags": ["beyblade", "rpb"]
    },
    {
      "id": "2020542271146324155",
      "text": "PRENEZ MOI. JE SUIS CHAUD.",
      "createdAt": "2026-02-08T16:56:31Z",
      "replyCount": 2,
      "retweetCount": 0,
      "likeCount": 3
    },
    {
      "id": "2020523883623751969",
      "text": "Moi au prochain tournoi Beyblade o\u00f9 je serais pr\u00e9sent :",
      "createdAt": "2026-02-08T15:43:28Z",
      "replyCount": 4,
      "retweetCount": 1,
      "likeCount": 5,
      "tags": ["beyblade", "tournament"]
    },
    {
      "id": "2020291093565436268",
      "text": "Le conseil des Kage \u00e0 la recherche du One Piece AHAHAHAHAHAAHAHAHAHAHAHAHAAHAHAHAHAHAHAAHHAHAAHAH (personne n'a la ref et c'est TR\u00c8S DR\u00d4LE)",
      "createdAt": "2026-02-08T00:18:26Z",
      "replyCount": 1,
      "retweetCount": 2,
      "likeCount": 6
    },
    {
      "id": "2020227405861040224",
      "text": "La sc\u00e8ne Beyblade est en train de partir en couille avec ces prizes de fou du bus",
      "createdAt": "2026-02-07T20:05:22Z",
      "replyCount": 0,
      "retweetCount": 0,
      "likeCount": 8,
      "tags": ["beyblade"]
    },
    {
      "id": "2019757888458064003",
      "text": "C'est vraiment le pire pr\u00e9sident de l'histoire, et il le prouve \u00e0 nouveau chaque jour",
      "createdAt": "2026-02-06T12:59:40Z",
      "replyCount": 0,
      "retweetCount": 0,
      "likeCount": 4
    },
    {
      "id": "2019509834601906474",
      "text": "RT @pokkoliidlc: j'ai toujours r\u00eav\u00e9 de ratio Renaissance",
      "createdAt": "2026-02-05T20:33:59Z",
      "isRetweet": true
    },
    {
      "id": "2019419503764119722",
      "text": "RT @FraudeurDuFisk: On est le jeudi 5 F\u00e9vrier big d\u00e9dicace...",
      "createdAt": "2026-02-05T14:35:03Z",
      "isRetweet": true
    },
    {
      "id": "2019418933477224779",
      "text": "RT @Dweezzzz: @20Minutes Allez vous faire enculer",
      "createdAt": "2026-02-05T14:32:47Z",
      "isRetweet": true
    },
    {
      "id": "2019418658699985109",
      "text": "RT @Noirissime_: Demain 18h je stream Inazuma Eleven GO CS episodes 1 a 4 sur Twitch",
      "createdAt": "2026-02-05T14:31:41Z",
      "isRetweet": true
    }
  ]
}
